{
  "_id": 408410,
  "id": "sweet_dreams_soda",
  "name": "Soda de dulces sueños",
  "description": "Tras su uso, el Daño de Fuego que reciban todos los aliados disminuye en un 10% en la siguiente batalla.",
  "story": "Una bebida de Colonipenal, el planeta de las celebraciones, llamada FelizAlma. Tiene el efecto de ayudar a conciliar el sueño y calmar la mente. Al beberla, da la sensación de estar en un hermoso sueño. Esta versión de la fórmula se ha ajustado para adaptarse mejor a los gustos de los consumidores de Xianzhou. Se dice que solo en los sueños de Colonipenal se puede saborear la Primera FelizAlma, supuestamente tan deliciosa como el néctar divino.\n\n\"¡Un sorbo de FelizAlma hará que tus sueños más maravillosos se vuelvan realidad!\".",
  "rarity": 2,
  "source": [
    {
      "description": "Oficina de compra de paquetes caducados",
      "recipe": []
    }
  ],
  "type": {
    "id": 10,
    "name": "Consumible"
  }
}