{
  "_id": 1301,
  "id": "gallagher",
  "name": "加拉赫",
  "rarity": 4,
  "combat_type": {
    "id": "fire",
    "name": "火"
  },
  "path": {
    "id": "abundance",
    "name": "豐饒"
  },
  "faction": {
    "_id": 108,
    "id": "penacony",
    "name": "匹諾康尼"
  },
  "cv": {
    "english": "马语非",
    "chinese": "马语非",
    "japanese": "三上哲",
    "korean": "박상훈"
  },
  "ascends": [
    {
      "promotion": 0,
      "maxLevel": 20,
      "materials": [
        {
          "_id": 2,
          "id": "credit",
          "name": "信用點",
          "amount": 3200
        },
        {
          "_id": 114001,
          "id": "dream_collection_component",
          "name": "蓄夢元件",
          "amount": 4
        }
      ],
      "attackBase": 72,
      "attackAdd": 3.6,
      "hpBase": 177.6,
      "hpAdd": 8.88,
      "defenseBase": 60,
      "defenseAdd": 3,
      "crate": 0.05,
      "cdmg": 0.5,
      "aggro": 100,
      "speedBase": 98,
      "speedAdd": 0
    },
    {
      "promotion": 1,
      "maxLevel": 30,
      "materials": [
        {
          "_id": 2,
          "id": "credit",
          "name": "信用點",
          "amount": 6400
        },
        {
          "_id": 114001,
          "id": "dream_collection_component",
          "name": "蓄夢元件",
          "amount": 8
        }
      ],
      "attackBase": 100.8,
      "attackAdd": 3.6,
      "hpBase": 248.64,
      "hpAdd": 8.88,
      "defenseBase": 84,
      "defenseAdd": 3,
      "crate": 0.05,
      "cdmg": 0.5,
      "aggro": 100,
      "speedBase": 98,
      "speedAdd": 0
    },
    {
      "promotion": 2,
      "maxLevel": 40,
      "materials": [
        {
          "_id": 2,
          "id": "credit",
          "name": "信用點",
          "amount": 12800
        },
        {
          "_id": 114002,
          "id": "dream_flow_valve",
          "name": "流夢閥門",
          "amount": 5
        },
        {
          "_id": 110422,
          "id": "raging_heart",
          "name": "忿火之心",
          "amount": 2
        }
      ],
      "attackBase": 129.6,
      "attackAdd": 3.6,
      "hpBase": 319.68,
      "hpAdd": 8.88,
      "defenseBase": 108,
      "defenseAdd": 3,
      "crate": 0.05,
      "cdmg": 0.5,
      "aggro": 100,
      "speedBase": 98,
      "speedAdd": 0
    },
    {
      "promotion": 3,
      "maxLevel": 50,
      "materials": [
        {
          "_id": 2,
          "id": "credit",
          "name": "信用點",
          "amount": 32000
        },
        {
          "_id": 114002,
          "id": "dream_flow_valve",
          "name": "流夢閥門",
          "amount": 8
        },
        {
          "_id": 110422,
          "id": "raging_heart",
          "name": "忿火之心",
          "amount": 5
        }
      ],
      "attackBase": 158.4,
      "attackAdd": 3.6,
      "hpBase": 390.72,
      "hpAdd": 8.88,
      "defenseBase": 132,
      "defenseAdd": 3,
      "crate": 0.05,
      "cdmg": 0.5,
      "aggro": 100,
      "speedBase": 98,
      "speedAdd": 0
    },
    {
      "promotion": 4,
      "maxLevel": 60,
      "materials": [
        {
          "_id": 2,
          "id": "credit",
          "name": "信用點",
          "amount": 64000
        },
        {
          "_id": 114003,
          "id": "dream_making_engine",
          "name": "造夢馬達",
          "amount": 5
        },
        {
          "_id": 110422,
          "id": "raging_heart",
          "name": "忿火之心",
          "amount": 15
        }
      ],
      "attackBase": 187.2,
      "attackAdd": 3.6,
      "hpBase": 461.76,
      "hpAdd": 8.88,
      "defenseBase": 156,
      "defenseAdd": 3,
      "crate": 0.05,
      "cdmg": 0.5,
      "aggro": 100,
      "speedBase": 98,
      "speedAdd": 0
    },
    {
      "promotion": 5,
      "maxLevel": 70,
      "materials": [
        {
          "_id": 2,
          "id": "credit",
          "name": "信用點",
          "amount": 128000
        },
        {
          "_id": 114003,
          "id": "dream_making_engine",
          "name": "造夢馬達",
          "amount": 7
        },
        {
          "_id": 110422,
          "id": "raging_heart",
          "name": "忿火之心",
          "amount": 28
        }
      ],
      "attackBase": 216,
      "attackAdd": 3.6,
      "hpBase": 532.8,
      "hpAdd": 8.88,
      "defenseBase": 180,
      "defenseAdd": 3,
      "crate": 0.05,
      "cdmg": 0.5,
      "aggro": 100,
      "speedBase": 98,
      "speedAdd": 0
    },
    {
      "promotion": 6,
      "maxLevel": 80,
      "materials": [],
      "attackBase": 244.8,
      "attackAdd": 3.6,
      "hpBase": 603.84,
      "hpAdd": 8.88,
      "defenseBase": 204,
      "defenseAdd": 3,
      "crate": 0.05,
      "cdmg": 0.5,
      "aggro": 100,
      "speedBase": 98,
      "speedAdd": 0
    }
  ],
  "skills": [
    {
      "_id": 130101,
      "id": "corkage_fee",
      "name": "開瓶費",
      "desc": "對指定敵方單體造成等同於加拉赫#1[i]%攻擊力的火屬性傷害。",
      "simpleDesc": "對敵方單體造成少量火屬性傷害。",
      "type": "普通攻擊",
      "tag": "單體攻擊",
      "levels": [
        {
          "level": 1,
          "params": [
            0.5
          ],
          "materials": []
        },
        {
          "level": 2,
          "params": [
            0.6
          ],
          "materials": [
            {
              "_id": 2,
              "id": "credit",
              "name": "信用點",
              "amount": 4000
            },
            {
              "_id": 110241,
              "id": "alien_tree_seed",
              "name": "異木種籽",
              "amount": 2
            },
            {
              "_id": 114001,
              "id": "dream_collection_component",
              "name": "蓄夢元件",
              "amount": 4
            }
          ]
        },
        {
          "level": 3,
          "params": [
            0.7
          ],
          "materials": [
            {
              "_id": 2,
              "id": "credit",
              "name": "信用點",
              "amount": 8000
            },
            {
              "_id": 110242,
              "id": "nourishing_honey",
              "name": "滋長花蜜",
              "amount": 2
            },
            {
              "_id": 114002,
              "id": "dream_flow_valve",
              "name": "流夢閥門",
              "amount": 2
            }
          ]
        },
        {
          "level": 4,
          "params": [
            0.8
          ],
          "materials": [
            {
              "_id": 2,
              "id": "credit",
              "name": "信用點",
              "amount": 16000
            },
            {
              "_id": 110242,
              "id": "nourishing_honey",
              "name": "滋長花蜜",
              "amount": 4
            },
            {
              "_id": 114002,
              "id": "dream_flow_valve",
              "name": "流夢閥門",
              "amount": 3
            }
          ]
        },
        {
          "level": 5,
          "params": [
            0.9
          ],
          "materials": [
            {
              "_id": 2,
              "id": "credit",
              "name": "信用點",
              "amount": 36000
            },
            {
              "_id": 110243,
              "id": "myriad_fruit",
              "name": "萬相果實",
              "amount": 2
            },
            {
              "_id": 114003,
              "id": "dream_making_engine",
              "name": "造夢馬達",
              "amount": 2
            }
          ]
        },
        {
          "level": 6,
          "params": [
            1
          ],
          "materials": [
            {
              "_id": 2,
              "id": "credit",
              "name": "信用點",
              "amount": 128000
            },
            {
              "_id": 110243,
              "id": "myriad_fruit",
              "name": "萬相果實",
              "amount": 6
            },
            {
              "_id": 114003,
              "id": "dream_making_engine",
              "name": "造夢馬達",
              "amount": 3
            }
          ]
        },
        {
          "level": 7,
          "params": [
            1.1
          ]
        },
        {
          "level": 8,
          "params": [
            1.2
          ]
        },
        {
          "level": 9,
          "params": [
            1.3
          ]
        }
      ]
    },
    {
      "_id": 130102,
      "id": "special_brew",
      "name": "罐裝特調",
      "desc": "立即為指定我方單體回復#1[i]點生命值。",
      "simpleDesc": "立即為我方單體回復生命值。",
      "type": "戰技",
      "tag": "回復",
      "levels": [
        {
          "level": 1,
          "params": [
            200
          ],
          "materials": []
        },
        {
          "level": 2,
          "params": [
            340
          ],
          "materials": [
            {
              "_id": 2,
              "id": "credit",
              "name": "信用點",
              "amount": 2000
            },
            {
              "_id": 114001,
              "id": "dream_collection_component",
              "name": "蓄夢元件",
              "amount": 2
            }
          ]
        },
        {
          "level": 3,
          "params": [
            480
          ],
          "materials": [
            {
              "_id": 2,
              "id": "credit",
              "name": "信用點",
              "amount": 4000
            },
            {
              "_id": 110241,
              "id": "alien_tree_seed",
              "name": "異木種籽",
              "amount": 2
            },
            {
              "_id": 114001,
              "id": "dream_collection_component",
              "name": "蓄夢元件",
              "amount": 4
            }
          ]
        },
        {
          "level": 4,
          "params": [
            676
          ],
          "materials": [
            {
              "_id": 2,
              "id": "credit",
              "name": "信用點",
              "amount": 8000
            },
            {
              "_id": 110242,
              "id": "nourishing_honey",
              "name": "滋長花蜜",
              "amount": 2
            },
            {
              "_id": 114002,
              "id": "dream_flow_valve",
              "name": "流夢閥門",
              "amount": 2
            }
          ]
        },
        {
          "level": 5,
          "params": [
            830
          ],
          "materials": [
            {
              "_id": 2,
              "id": "credit",
              "name": "信用點",
              "amount": 16000
            },
            {
              "_id": 110242,
              "id": "nourishing_honey",
              "name": "滋長花蜜",
              "amount": 4
            },
            {
              "_id": 114002,
              "id": "dream_flow_valve",
              "name": "流夢閥門",
              "amount": 3
            }
          ]
        },
        {
          "level": 6,
          "params": [
            984
          ],
          "materials": [
            {
              "_id": 2,
              "id": "credit",
              "name": "信用點",
              "amount": 24000
            },
            {
              "_id": 110242,
              "id": "nourishing_honey",
              "name": "滋長花蜜",
              "amount": 6
            },
            {
              "_id": 114002,
              "id": "dream_flow_valve",
              "name": "流夢閥門",
              "amount": 5
            }
          ]
        },
        {
          "level": 7,
          "params": [
            1138
          ],
          "materials": [
            {
              "_id": 2,
              "id": "credit",
              "name": "信用點",
              "amount": 36000
            },
            {
              "_id": 110243,
              "id": "myriad_fruit",
              "name": "萬相果實",
              "amount": 2
            },
            {
              "_id": 114003,
              "id": "dream_making_engine",
              "name": "造夢馬達",
              "amount": 2
            }
          ]
        },
        {
          "level": 8,
          "params": [
            1292
          ],
          "materials": [
            {
              "_id": 2,
              "id": "credit",
              "name": "信用點",
              "amount": 64000
            },
            {
              "_id": 110243,
              "id": "myriad_fruit",
              "name": "萬相果實",
              "amount": 4
            },
            {
              "_id": 110504,
              "id": "past_evils_of_the_borehole_planet_disaster",
              "name": "蛀星孕災的舊惡",
              "amount": 1
            },
            {
              "_id": 114003,
              "id": "dream_making_engine",
              "name": "造夢馬達",
              "amount": 3
            }
          ]
        },
        {
          "level": 9,
          "params": [
            1446
          ],
          "materials": [
            {
              "_id": 2,
              "id": "credit",
              "name": "信用點",
              "amount": 128000
            },
            {
              "_id": 110243,
              "id": "myriad_fruit",
              "name": "萬相果實",
              "amount": 6
            },
            {
              "_id": 110504,
              "id": "past_evils_of_the_borehole_planet_disaster",
              "name": "蛀星孕災的舊惡",
              "amount": 1
            }
          ]
        },
        {
          "level": 10,
          "params": [
            1600
          ],
          "materials": [
            {
              "_id": 2,
              "id": "credit",
              "name": "信用點",
              "amount": 240000
            },
            {
              "_id": 110243,
              "id": "myriad_fruit",
              "name": "萬相果實",
              "amount": 11
            },
            {
              "_id": 241,
              "id": "tracks_of_destiny",
              "name": "命運的足跡",
              "amount": 1
            },
            {
              "_id": 110504,
              "id": "past_evils_of_the_borehole_planet_disaster",
              "name": "蛀星孕災的舊惡",
              "amount": 1
            }
          ]
        },
        {
          "level": 11,
          "params": [
            1684
          ]
        },
        {
          "level": 12,
          "params": [
            1768
          ]
        },
        {
          "level": 13,
          "params": [
            1852
          ]
        },
        {
          "level": 14,
          "params": [
            1936
          ]
        },
        {
          "level": 15,
          "params": [
            2020
          ]
        }
      ]
    },
    {
      "_id": 130103,
      "id": "champagne_etiquette",
      "name": "香檳儀禮",
      "desc": "使敵方全體陷入【酩酊】狀態，持續#2[i]回合，同時對敵方全體造成等同於加拉赫#1[i]%攻擊力的火屬性傷害，並將下一次普通攻擊強化為【酒花奔湧】。",
      "simpleDesc": "使敵方全體陷入【酩酊】狀態，同時對敵方全體造成火屬性傷害。下一次普通攻擊強化為【酒花奔湧】。",
      "type": "終結技",
      "tag": "群體攻擊",
      "levels": [
        {
          "level": 1,
          "params": [
            0.75,
            2
          ],
          "materials": []
        },
        {
          "level": 2,
          "params": [
            0.82,
            2
          ],
          "materials": [
            {
              "_id": 2,
              "id": "credit",
              "name": "信用點",
              "amount": 2000
            },
            {
              "_id": 114001,
              "id": "dream_collection_component",
              "name": "蓄夢元件",
              "amount": 2
            }
          ]
        },
        {
          "level": 3,
          "params": [
            0.9,
            2
          ],
          "materials": [
            {
              "_id": 2,
              "id": "credit",
              "name": "信用點",
              "amount": 4000
            },
            {
              "_id": 110241,
              "id": "alien_tree_seed",
              "name": "異木種籽",
              "amount": 2
            },
            {
              "_id": 114001,
              "id": "dream_collection_component",
              "name": "蓄夢元件",
              "amount": 4
            }
          ]
        },
        {
          "level": 4,
          "params": [
            0.97,
            2
          ],
          "materials": [
            {
              "_id": 2,
              "id": "credit",
              "name": "信用點",
              "amount": 8000
            },
            {
              "_id": 110242,
              "id": "nourishing_honey",
              "name": "滋長花蜜",
              "amount": 2
            },
            {
              "_id": 114002,
              "id": "dream_flow_valve",
              "name": "流夢閥門",
              "amount": 2
            }
          ]
        },
        {
          "level": 5,
          "params": [
            1.05,
            2
          ],
          "materials": [
            {
              "_id": 2,
              "id": "credit",
              "name": "信用點",
              "amount": 16000
            },
            {
              "_id": 110242,
              "id": "nourishing_honey",
              "name": "滋長花蜜",
              "amount": 4
            },
            {
              "_id": 114002,
              "id": "dream_flow_valve",
              "name": "流夢閥門",
              "amount": 3
            }
          ]
        },
        {
          "level": 6,
          "params": [
            1.13,
            2
          ],
          "materials": [
            {
              "_id": 2,
              "id": "credit",
              "name": "信用點",
              "amount": 24000
            },
            {
              "_id": 110242,
              "id": "nourishing_honey",
              "name": "滋長花蜜",
              "amount": 6
            },
            {
              "_id": 114002,
              "id": "dream_flow_valve",
              "name": "流夢閥門",
              "amount": 5
            }
          ]
        },
        {
          "level": 7,
          "params": [
            1.22,
            2
          ],
          "materials": [
            {
              "_id": 2,
              "id": "credit",
              "name": "信用點",
              "amount": 36000
            },
            {
              "_id": 110243,
              "id": "myriad_fruit",
              "name": "萬相果實",
              "amount": 2
            },
            {
              "_id": 114003,
              "id": "dream_making_engine",
              "name": "造夢馬達",
              "amount": 2
            }
          ]
        },
        {
          "level": 8,
          "params": [
            1.31,
            2
          ],
          "materials": [
            {
              "_id": 2,
              "id": "credit",
              "name": "信用點",
              "amount": 64000
            },
            {
              "_id": 110243,
              "id": "myriad_fruit",
              "name": "萬相果實",
              "amount": 4
            },
            {
              "_id": 110504,
              "id": "past_evils_of_the_borehole_planet_disaster",
              "name": "蛀星孕災的舊惡",
              "amount": 1
            },
            {
              "_id": 114003,
              "id": "dream_making_engine",
              "name": "造夢馬達",
              "amount": 3
            }
          ]
        },
        {
          "level": 9,
          "params": [
            1.41,
            2
          ],
          "materials": [
            {
              "_id": 2,
              "id": "credit",
              "name": "信用點",
              "amount": 128000
            },
            {
              "_id": 110243,
              "id": "myriad_fruit",
              "name": "萬相果實",
              "amount": 6
            },
            {
              "_id": 110504,
              "id": "past_evils_of_the_borehole_planet_disaster",
              "name": "蛀星孕災的舊惡",
              "amount": 1
            }
          ]
        },
        {
          "level": 10,
          "params": [
            1.5,
            2
          ],
          "materials": [
            {
              "_id": 2,
              "id": "credit",
              "name": "信用點",
              "amount": 240000
            },
            {
              "_id": 110243,
              "id": "myriad_fruit",
              "name": "萬相果實",
              "amount": 11
            },
            {
              "_id": 241,
              "id": "tracks_of_destiny",
              "name": "命運的足跡",
              "amount": 1
            },
            {
              "_id": 110504,
              "id": "past_evils_of_the_borehole_planet_disaster",
              "name": "蛀星孕災的舊惡",
              "amount": 1
            }
          ]
        },
        {
          "level": 11,
          "params": [
            1.57,
            2
          ]
        },
        {
          "level": 12,
          "params": [
            1.65,
            2
          ]
        },
        {
          "level": 13,
          "params": [
            1.73,
            2
          ]
        },
        {
          "level": 14,
          "params": [
            1.8,
            2
          ]
        },
        {
          "level": 15,
          "params": [
            1.88,
            2
          ]
        }
      ]
    },
    {
      "_id": 130104,
      "id": "tipsy_tussle",
      "name": "鏖戰正酣",
      "desc": "【酩酊】使目標受到的擊破傷害提高#1[f1]%。陷入【酩酊】狀態的目標每次受到我方角色攻擊後，會回復攻擊者#2[i]點生命值。",
      "simpleDesc": "【酩酊】使目標受到的擊破傷害提高，目標每次受到我方角色攻擊後，攻擊者回復生命值。",
      "type": "天賦",
      "tag": "回復",
      "levels": [
        {
          "level": 1,
          "params": [
            0.06,
            80
          ],
          "materials": []
        },
        {
          "level": 2,
          "params": [
            0.07,
            136
          ],
          "materials": [
            {
              "_id": 2,
              "id": "credit",
              "name": "信用點",
              "amount": 2000
            },
            {
              "_id": 114001,
              "id": "dream_collection_component",
              "name": "蓄夢元件",
              "amount": 2
            }
          ]
        },
        {
          "level": 3,
          "params": [
            0.07,
            192
          ],
          "materials": [
            {
              "_id": 2,
              "id": "credit",
              "name": "信用點",
              "amount": 4000
            },
            {
              "_id": 110241,
              "id": "alien_tree_seed",
              "name": "異木種籽",
              "amount": 2
            },
            {
              "_id": 114001,
              "id": "dream_collection_component",
              "name": "蓄夢元件",
              "amount": 4
            }
          ]
        },
        {
          "level": 4,
          "params": [
            0.08,
            270.4
          ],
          "materials": [
            {
              "_id": 2,
              "id": "credit",
              "name": "信用點",
              "amount": 8000
            },
            {
              "_id": 110242,
              "id": "nourishing_honey",
              "name": "滋長花蜜",
              "amount": 2
            },
            {
              "_id": 114002,
              "id": "dream_flow_valve",
              "name": "流夢閥門",
              "amount": 2
            }
          ]
        },
        {
          "level": 5,
          "params": [
            0.08,
            332
          ],
          "materials": [
            {
              "_id": 2,
              "id": "credit",
              "name": "信用點",
              "amount": 16000
            },
            {
              "_id": 110242,
              "id": "nourishing_honey",
              "name": "滋長花蜜",
              "amount": 4
            },
            {
              "_id": 114002,
              "id": "dream_flow_valve",
              "name": "流夢閥門",
              "amount": 3
            }
          ]
        },
        {
          "level": 6,
          "params": [
            0.09,
            393.6
          ],
          "materials": [
            {
              "_id": 2,
              "id": "credit",
              "name": "信用點",
              "amount": 24000
            },
            {
              "_id": 110242,
              "id": "nourishing_honey",
              "name": "滋長花蜜",
              "amount": 6
            },
            {
              "_id": 114002,
              "id": "dream_flow_valve",
              "name": "流夢閥門",
              "amount": 5
            }
          ]
        },
        {
          "level": 7,
          "params": [
            0.1,
            455.2
          ],
          "materials": [
            {
              "_id": 2,
              "id": "credit",
              "name": "信用點",
              "amount": 36000
            },
            {
              "_id": 110243,
              "id": "myriad_fruit",
              "name": "萬相果實",
              "amount": 2
            },
            {
              "_id": 114003,
              "id": "dream_making_engine",
              "name": "造夢馬達",
              "amount": 2
            }
          ]
        },
        {
          "level": 8,
          "params": [
            0.1,
            516.8
          ],
          "materials": [
            {
              "_id": 2,
              "id": "credit",
              "name": "信用點",
              "amount": 64000
            },
            {
              "_id": 110243,
              "id": "myriad_fruit",
              "name": "萬相果實",
              "amount": 4
            },
            {
              "_id": 110504,
              "id": "past_evils_of_the_borehole_planet_disaster",
              "name": "蛀星孕災的舊惡",
              "amount": 1
            },
            {
              "_id": 114003,
              "id": "dream_making_engine",
              "name": "造夢馬達",
              "amount": 3
            }
          ]
        },
        {
          "level": 9,
          "params": [
            0.11,
            578.4
          ],
          "materials": [
            {
              "_id": 2,
              "id": "credit",
              "name": "信用點",
              "amount": 128000
            },
            {
              "_id": 110243,
              "id": "myriad_fruit",
              "name": "萬相果實",
              "amount": 6
            },
            {
              "_id": 110504,
              "id": "past_evils_of_the_borehole_planet_disaster",
              "name": "蛀星孕災的舊惡",
              "amount": 1
            }
          ]
        },
        {
          "level": 10,
          "params": [
            0.12,
            640
          ],
          "materials": [
            {
              "_id": 2,
              "id": "credit",
              "name": "信用點",
              "amount": 240000
            },
            {
              "_id": 110243,
              "id": "myriad_fruit",
              "name": "萬相果實",
              "amount": 11
            },
            {
              "_id": 241,
              "id": "tracks_of_destiny",
              "name": "命運的足跡",
              "amount": 1
            },
            {
              "_id": 110504,
              "id": "past_evils_of_the_borehole_planet_disaster",
              "name": "蛀星孕災的舊惡",
              "amount": 1
            }
          ]
        },
        {
          "level": 11,
          "params": [
            0.13,
            673.6
          ]
        },
        {
          "level": 12,
          "params": [
            0.13,
            707.2
          ]
        },
        {
          "level": 13,
          "params": [
            0.14,
            740.8
          ]
        },
        {
          "level": 14,
          "params": [
            0.14,
            774.4
          ]
        },
        {
          "level": 15,
          "params": [
            0.15,
            808
          ]
        }
      ]
    },
    {
      "_id": 130107,
      "id": "artisan_elixir",
      "name": "親啟佳釀",
      "desc": "立即攻擊敵人，進入戰鬥後使敵方全體陷入【酩酊】狀態，持續#1[i]回合，並對敵方全體造成等同於加拉赫#2[i]%攻擊力的火屬性傷害。",
      "simpleDesc": "攻擊敵人，進入戰鬥後使敵方全體陷入【酩酊】狀態，並對敵方全體造成少量火屬性傷害。",
      "type": "秘技",
      "levels": [
        {
          "level": 1,
          "params": [
            2,
            0.5
          ],
          "materials": []
        }
      ]
    }
  ],
  "eidolons": [
    {
      "_id": 130101,
      "id": "salty_dog",
      "name": "鹽與犬",
      "desc": "加拉赫進入戰鬥後會恢復<nobr>20</nobr>點能量，效果抗性提高<nobr>50%</nobr>。"
    },
    {
      "_id": 130102,
      "id": "lions_tail",
      "name": "獅子之尾",
      "desc": "施放戰技時，解除指定我方單體的<nobr>1</nobr>個<u>負面效果</u>，同時使其效果抗性提高<nobr>30%</nobr>，持續<nobr>2</nobr>回合。"
    },
    {
      "_id": 130103,
      "id": "corpse_reviver",
      "name": "逝者的新生",
      "desc": "戰技等級+2，最多不超過<nobr>15</nobr>級；普通攻擊等級+1，最多不超過<nobr>10</nobr>級。"
    },
    {
      "_id": 130104,
      "id": "last_word",
      "name": "臨終的輕語",
      "desc": "加拉赫終結技造成的【酩酊】狀態持續時間延長<nobr>1</nobr>回合。"
    },
    {
      "_id": 130105,
      "id": "death_in_the_afternoon",
      "name": "午後之死",
      "desc": "終結技等級+2，最多不超過<nobr>15</nobr>級；天賦等級+2，最多不超過<nobr>15</nobr>級。"
    },
    {
      "_id": 130106,
      "id": "blood_and_sand",
      "name": "血與沙",
      "desc": "加拉赫的擊破特攻提高<nobr>20%</nobr>，弱點擊破效率提高<nobr>20%</nobr>。"
    }
  ],
  "skillTreePoints": [
    {
      "id": 1301101,
      "type": 3,
      "children": [
        {
          "id": 1301202,
          "type": 1,
          "children": [
            {
              "id": 1301203,
              "type": 1,
              "children": [],
              "embedBuff": {
                "id": "effect_res_boost",
                "name": "效果抗性強化",
                "levelReq": 0,
                "promotionReq": 3,
                "statusList": [
                  {
                    "key": "效果抗性提高<nobr>#1[f1]%</nobr>",
                    "value": 0.04
                  }
                ],
                "materials": [
                  {
                    "id": "credit",
                    "name": "信用點",
                    "amount": 8000
                  },
                  {
                    "id": "nourishing_honey",
                    "name": "滋長花蜜",
                    "amount": 2
                  },
                  {
                    "id": "dream_flow_valve",
                    "name": "流夢閥門",
                    "amount": 2
                  }
                ]
              }
            }
          ],
          "embedBuff": {
            "id": "break_boost",
            "name": "擊破強化",
            "levelReq": 0,
            "promotionReq": 2,
            "statusList": [
              {
                "key": "擊破特攻提高<nobr>#1[f1]%</nobr>",
                "value": 0.053
              }
            ],
            "materials": [
              {
                "id": "credit",
                "name": "信用點",
                "amount": 4000
              },
              {
                "id": "alien_tree_seed",
                "name": "異木種籽",
                "amount": 2
              },
              {
                "id": "dream_collection_component",
                "name": "蓄夢元件",
                "amount": 4
              }
            ]
          }
        }
      ],
      "embedBonusSkill": {
        "id": "novel_concoction",
        "name": "嶄新配方",
        "desc": "使自身提供的治療量提高，提高數值等同於擊破特攻的<nobr>50%</nobr>，最多使提供的治療量提高<nobr>75%</nobr>。",
        "type": "",
        "tag": "",
        "levels": [
          {
            "level": 1,
            "params": [
              0.5,
              0.75
            ],
            "materials": [
              {
                "id": "credit",
                "name": "信用點",
                "amount": 4000
              },
              {
                "id": "alien_tree_seed",
                "name": "異木種籽",
                "amount": 2
              },
              {
                "id": "past_evils_of_the_borehole_planet_disaster",
                "name": "蛀星孕災的舊惡",
                "amount": 1
              }
            ]
          }
        ]
      }
    },
    {
      "id": 1301102,
      "type": 3,
      "children": [
        {
          "id": 1301205,
          "type": 1,
          "children": [
            {
              "id": 1301206,
              "type": 1,
              "children": [],
              "embedBuff": {
                "id": "break_boost",
                "name": "擊破強化",
                "levelReq": 0,
                "promotionReq": 5,
                "statusList": [
                  {
                    "key": "擊破特攻提高<nobr>#1[f1]%</nobr>",
                    "value": 0.08
                  }
                ],
                "materials": [
                  {
                    "id": "credit",
                    "name": "信用點",
                    "amount": 36000
                  },
                  {
                    "id": "myriad_fruit",
                    "name": "萬相果實",
                    "amount": 2
                  },
                  {
                    "id": "dream_making_engine",
                    "name": "造夢馬達",
                    "amount": 2
                  }
                ]
              }
            }
          ],
          "embedBuff": {
            "id": "effect_res_boost",
            "name": "效果抗性強化",
            "levelReq": 0,
            "promotionReq": 4,
            "statusList": [
              {
                "key": "效果抗性提高<nobr>#1[f1]%</nobr>",
                "value": 0.06
              }
            ],
            "materials": [
              {
                "id": "credit",
                "name": "信用點",
                "amount": 16000
              },
              {
                "id": "nourishing_honey",
                "name": "滋長花蜜",
                "amount": 4
              },
              {
                "id": "dream_flow_valve",
                "name": "流夢閥門",
                "amount": 3
              }
            ]
          }
        }
      ],
      "embedBonusSkill": {
        "id": "organic_yeast",
        "name": "天然酵母",
        "desc": "施放終結技後，立刻使自己<u>行動提前</u><nobr>100%</nobr>。",
        "type": "",
        "tag": "",
        "levels": [
          {
            "level": 1,
            "params": [],
            "materials": [
              {
                "id": "credit",
                "name": "信用點",
                "amount": 16000
              },
              {
                "id": "nourishing_honey",
                "name": "滋長花蜜",
                "amount": 4
              },
              {
                "id": "tracks_of_destiny",
                "name": "命運的足跡",
                "amount": 1
              },
              {
                "id": "past_evils_of_the_borehole_planet_disaster",
                "name": "蛀星孕災的舊惡",
                "amount": 1
              }
            ]
          }
        ]
      }
    },
    {
      "id": 1301103,
      "type": 3,
      "children": [
        {
          "id": 1301208,
          "type": 1,
          "children": [],
          "embedBuff": {
            "id": "hp_boost",
            "name": "生命強化",
            "levelReq": 0,
            "promotionReq": 6,
            "statusList": [
              {
                "key": "生命上限提高<nobr>#1[f1]%</nobr>",
                "value": 0.06
              }
            ],
            "materials": [
              {
                "id": "credit",
                "name": "信用點",
                "amount": 128000
              },
              {
                "id": "myriad_fruit",
                "name": "萬相果實",
                "amount": 6
              },
              {
                "id": "dream_making_engine",
                "name": "造夢馬達",
                "amount": 6
              }
            ]
          }
        },
        {
          "id": 1301209,
          "type": 1,
          "children": [],
          "embedBuff": {
            "id": "effect_res_boost",
            "name": "效果抗性強化",
            "levelReq": 75,
            "promotionReq": 0,
            "statusList": [
              {
                "key": "效果抗性提高<nobr>#1[f1]%</nobr>",
                "value": 0.08
              }
            ],
            "materials": [
              {
                "id": "credit",
                "name": "信用點",
                "amount": 128000
              },
              {
                "id": "myriad_fruit",
                "name": "萬相果實",
                "amount": 6
              },
              {
                "id": "dream_making_engine",
                "name": "造夢馬達",
                "amount": 6
              }
            ]
          }
        }
      ],
      "embedBonusSkill": {
        "id": "bottoms_up",
        "name": "敬請乾杯",
        "desc": "加拉赫施放【酒花奔湧】攻擊陷入【酩酊】狀態的目標時，此次天賦提供的生命回復效果也會對我方隊友生效。",
        "type": "",
        "tag": "",
        "levels": [
          {
            "level": 1,
            "params": [],
            "materials": [
              {
                "id": "credit",
                "name": "信用點",
                "amount": 128000
              },
              {
                "id": "myriad_fruit",
                "name": "萬相果實",
                "amount": 6
              },
              {
                "id": "tracks_of_destiny",
                "name": "命運的足跡",
                "amount": 1
              },
              {
                "id": "past_evils_of_the_borehole_planet_disaster",
                "name": "蛀星孕災的舊惡",
                "amount": 1
              }
            ]
          }
        ]
      }
    },
    {
      "id": 1301201,
      "type": 1,
      "children": [],
      "embedBuff": {
        "id": "effect_res_boost",
        "name": "效果抗性強化",
        "levelReq": 1,
        "promotionReq": 0,
        "statusList": [
          {
            "key": "效果抗性提高<nobr>#1[f1]%</nobr>",
            "value": 0.04
          }
        ],
        "materials": [
          {
            "id": "credit",
            "name": "信用點",
            "amount": 2000
          },
          {
            "id": "dream_collection_component",
            "name": "蓄夢元件",
            "amount": 2
          }
        ]
      }
    },
    {
      "id": 1301210,
      "type": 1,
      "children": [],
      "embedBuff": {
        "id": "hp_boost",
        "name": "生命強化",
        "levelReq": 80,
        "promotionReq": 0,
        "statusList": [
          {
            "key": "生命上限提高<nobr>#1[f1]%</nobr>",
            "value": 0.08
          }
        ],
        "materials": [
          {
            "id": "credit",
            "name": "信用點",
            "amount": 128000
          },
          {
            "id": "myriad_fruit",
            "name": "萬相果實",
            "amount": 6
          },
          {
            "id": "dream_making_engine",
            "name": "造夢馬達",
            "amount": 6
          }
        ]
      }
    }
  ]
}