{
  "_id": 402012,
  "id": "enhancement_paste_ice",
  "name": "強化軟膏：氷",
  "description": "使用後、次の戦闘で味方全体の氷属性与ダメージ+24%。",
  "story": "運命の力を宿している素材を他の物質をすりつぶして混ぜた膏薬。\nこの軟膏を武器に塗ると、強化できる。\n\n「労力は半分で、功績は倍」",
  "rarity": 3,
  "source": [
    {
      "description": "「万能合成マシン」",
      "recipe": [
        {
          "materialCost": [
            {
              "id": 180001,
              "name": "固形純水",
              "rarity": 1,
              "count": 5
            },
            {
              "id": 181005,
              "name": "氷の芯",
              "rarity": 2,
              "count": 2
            },
            {
              "id": 182006,
              "name": "知恵の樹皮",
              "rarity": 3,
              "count": 2
            }
          ],
          "specialMaterialCost": []
        }
      ]
    }
  ],
  "type": {
    "id": 10,
    "name": "消耗品"
  }
}