{
  "_id": 403013,
  "id": "veil_bundle",
  "name": "永夜の帳の小包",
  "description": "使用後、味方全体が次の戦闘時にランダムで効果を1つ得る：速度+20%、撃破特効+60%、効果命中+60%。",
  "story": "中身のわからない小包、オンパロスの隊商でよく販売されている。麻紐で適当にまとめられたそれは、誰かが捨てたゴミかもしれないし、タイタンからの贈り物という可能性もある。開けた時には大なり小なり変化がもたらされるだろう。オロニクスの信者たちの習わしでは、予測不能なこの商品は、運命にテミスを捧げる儀式であり、価値を定める権利を、変わり続ける永夜の帳に委ねているのだという。\n\n「ケケケ、こいつは祖師ザグレウス様がでっちあげたんだ。これを買った信者も、別に信心深いわけじゃない——ただ、何が出るのか気になってしょうがないだけなんだ～！」\n",
  "rarity": 5,
  "source": [
    {
      "description": "「万能合成マシン」",
      "recipe": [
        {
          "materialCost": [
            {
              "id": 183007,
              "name": "黎明の種",
              "rarity": 5,
              "count": 2
            },
            {
              "id": 182011,
              "name": "絹糸の紡錘",
              "rarity": 3,
              "count": 2
            },
            {
              "id": 181017,
              "name": "思惟の枝",
              "rarity": 2,
              "count": 2
            },
            {
              "id": 180013,
              "name": "鮮やかな残羽",
              "rarity": 1,
              "count": 3
            }
          ],
          "specialMaterialCost": []
        }
      ]
    },
    {
      "description": "大地獣の行商隊（行商人）",
      "recipe": []
    }
  ],
  "type": {
    "id": 10,
    "name": "消耗品"
  }
}