{
  "_id": 408403,
  "id": "wild_herb_soup",
  "name": "Wild Herb Soup",
  "description": "หลังจากใช้งาน จะทำให้ฝ่ายตัวเองทั้งหมดเสีย HP 15% ของ HP สูงสุดของแต่ละตัวทันที และในการต่อสู้ครั้งถัดไป ATK ของฝ่ายตัวเองทั้งหมดจะเพิ่มขึ้น 200 หน่วย",
  "story": "มอสส์ที่พบเห็นได้ทั่วไปในใต้ดิน มันเปล่งแสงสีฟ้าจางๆ ที่ทำให้รู้สึกสงบออกมา แต่ถูกนำมาทำเป็นซุป\nว่ากันว่าก้อนมอสส์ชนิดนี้ มีผลช่วยคลายร้อนและล้างพิษได้ แต่โดยทั่วไปจะไม่แนะนำให้บริโภคผลิตภัณฑ์จาก Corrosive Ore Moss ที่ยังเรืองแสงอยู่\n\n\"ดื่มมันสิ... นี่คือโชคชะตาของชาว Belobog\"",
  "rarity": 2,
  "source": [
    {
      "description": "แผงขายอาหาร",
      "recipe": []
    }
  ],
  "type": {
    "id": 10,
    "name": "วัสดุใช้งาน"
  }
}
