{
  "_id": 408627,
  "id": "soundless_satisfaction",
  "name": "Stille Selbstgefälligkeit",
  "description": "Erhöht nach der Verwendung den Standardangriff-SCH aller Verbündeten für den nächsten Kampf um 45 % und reduziert den Fertigkeits-SCH um 12 %.",
  "story": "Vielleicht wollen die Menschen lieber anderen gefallen, als sich selbst zufriedenzustellen. Dennoch, lieber Freund, hoffe ich, dass du ein Lied für dich selbst spielen wirst, das niemand sonst kennt oder hört. Und dann brich in Gelächter aus – als Publikum und als Darsteller.\n\n„Das Leben ist wie ein großer Monolog.“",
  "rarity": 3,
  "source": [
    {
      "description": "Automatischer Musikladen",
      "recipe": []
    }
  ],
  "type": {
    "id": 10,
    "name": "Verbrauchsgegenstände"
  }
}