{
  "_id": 408001,
  "id": "trash",
  "name": "Müll",
  "description": "Nach der Verwendung verliert ein anvisierter Verbündeter sofort LP in Höhe von 15 % seiner max. LP.",
  "story": "Wertloser Abfall.\nImmer gut, welchen dabei zu haben.\n\n„Manche sagen, dass sich in den Tiefen der Galaxie ein unsichtbarer Teleporter für diejenigen öffnet, die etwas Müll mit sich führen.“",
  "rarity": 1,
  "source": [
    {
      "description": "Jarilo-VI: Zerstörbare Objekte",
      "recipe": []
    }
  ],
  "type": {
    "id": 10,
    "name": "Verbrauchsgegenstände"
  }
}
