{
  "_id": 24002,
  "id": "texture_of_memories",
  "name": "记忆的质料",
  "rarity": 5,
  "pathType": "Knight",
  "pathTypeText": "存护",
  "effectName": "珍存",
  "effectTemplate": "使装备者的效果抵抗提高<color=#f29e38ff>#1[i]%</color>，当装备者受到攻击后，如果自身未持有护盾，则获得1个等同于装备者<color=#f29e38ff>#2[i]%</color>生命上限的护盾，持续#3[i]回合。该效果每#4[i]回合只能触发1次。如果装备者持有护盾，则使自身受到的伤害降低<color=#f29e38ff>#5[i]%</color>。",
  "superImpositions": [
    {
      "rank": 1,
      "effect": "使装备者的效果抵抗提高<span style=\"color:#f29e38ff><nobr>8%</nobr></span>，当装备者受到攻击后，如果自身未持有护盾，则获得1个等同于装备者<span style=\"color:#f29e38ff><nobr>16%</nobr></span>生命上限的护盾，持续<nobr>2</nobr>回合。该效果每<nobr>3</nobr>回合只能触发1次。如果装备者持有护盾，则使自身受到的伤害降低<span style=\"color:#f29e38ff><nobr>12%</nobr></span>。",
      "params": ["8%", "16%", "2", "3", "12%"]
    },
    {
      "rank": 2,
      "effect": "使装备者的效果抵抗提高<span style=\"color:#f29e38ff><nobr>10%</nobr></span>，当装备者受到攻击后，如果自身未持有护盾，则获得1个等同于装备者<span style=\"color:#f29e38ff><nobr>20%</nobr></span>生命上限的护盾，持续<nobr>2</nobr>回合。该效果每<nobr>3</nobr>回合只能触发1次。如果装备者持有护盾，则使自身受到的伤害降低<span style=\"color:#f29e38ff><nobr>15%</nobr></span>。",
      "params": ["10%", "20%", "2", "3", "15%"]
    },
    {
      "rank": 3,
      "effect": "使装备者的效果抵抗提高<span style=\"color:#f29e38ff><nobr>12%</nobr></span>，当装备者受到攻击后，如果自身未持有护盾，则获得1个等同于装备者<span style=\"color:#f29e38ff><nobr>24%</nobr></span>生命上限的护盾，持续<nobr>2</nobr>回合。该效果每<nobr>3</nobr>回合只能触发1次。如果装备者持有护盾，则使自身受到的伤害降低<span style=\"color:#f29e38ff><nobr>18%</nobr></span>。",
      "params": ["12%", "24%", "2", "3", "18%"]
    },
    {
      "rank": 4,
      "effect": "使装备者的效果抵抗提高<span style=\"color:#f29e38ff><nobr>14%</nobr></span>，当装备者受到攻击后，如果自身未持有护盾，则获得1个等同于装备者<span style=\"color:#f29e38ff><nobr>28%</nobr></span>生命上限的护盾，持续<nobr>2</nobr>回合。该效果每<nobr>3</nobr>回合只能触发1次。如果装备者持有护盾，则使自身受到的伤害降低<span style=\"color:#f29e38ff><nobr>21%</nobr></span>。",
      "params": ["14%", "28%", "2", "3", "21%"]
    },
    {
      "rank": 5,
      "effect": "使装备者的效果抵抗提高<span style=\"color:#f29e38ff><nobr>16%</nobr></span>，当装备者受到攻击后，如果自身未持有护盾，则获得1个等同于装备者<span style=\"color:#f29e38ff><nobr>32%</nobr></span>生命上限的护盾，持续<nobr>2</nobr>回合。该效果每<nobr>3</nobr>回合只能触发1次。如果装备者持有护盾，则使自身受到的伤害降低<span style=\"color:#f29e38ff><nobr>24%</nobr></span>。",
      "params": ["16%", "32%", "2", "3", "24%"]
    }
  ],
  "ascend": [
    {
      "promotion": 0,
      "maxLevel": 20,
      "levelReq": 15,
      "attackBase": 19.199999698875853,
      "attackAdd": 2.8799999556230023,
      "hpBase": 47.999999246723974,
      "hpAdd": 7.19999988719486,
      "defenseBase": 23.999999623361987,
      "defenseAdd": 3.599999944063091,
      "materials": [
        {
          "_id": 2,
          "id": "credit",
          "name": "信用点",
          "amount": 5000
        },
        {
          "_id": 111001,
          "id": "extinguished_core",
          "name": "熄灭原核",
          "amount": 8
        }
      ]
    },
    {
      "promotion": 1,
      "maxLevel": 30,
      "attackBase": 42.23999933734061,
      "attackAdd": 2.8799999556230023,
      "hpBase": 105.59999834335153,
      "hpAdd": 7.19999988719486,
      "defenseBase": 52.799999172141426,
      "defenseAdd": 3.599999944063091,
      "materials": [
        {
          "_id": 2,
          "id": "credit",
          "name": "信用点",
          "amount": 10000
        },
        {
          "_id": 110141,
          "id": "endurance_of_bronze",
          "name": "青铜的执着",
          "amount": 4
        },
        {
          "_id": 111001,
          "id": "extinguished_core",
          "name": "熄灭原核",
          "amount": 12
        }
      ]
    },
    {
      "promotion": 2,
      "maxLevel": 40,
      "attackBase": 72.9599988559145,
      "attackAdd": 2.8799999556230023,
      "hpBase": 182.39999713792363,
      "hpAdd": 7.19999988719486,
      "defenseBase": 91.19999856896182,
      "defenseAdd": 3.599999944063091,
      "materials": [
        {
          "_id": 2,
          "id": "credit",
          "name": "信用点",
          "amount": 20000
        },
        {
          "_id": 110142,
          "id": "oath_of_steel",
          "name": "寒铁的誓言",
          "amount": 4
        },
        {
          "_id": 111002,
          "id": "glimmering_core",
          "name": "微光原核",
          "amount": 8
        }
      ]
    },
    {
      "promotion": 3,
      "maxLevel": 50,
      "attackBase": 103.67999837355708,
      "attackAdd": 2.8799999556230023,
      "hpBase": 259.1999959324957,
      "hpAdd": 7.19999988719486,
      "defenseBase": 129.59999796671352,
      "defenseAdd": 3.599999944063091,
      "materials": [
        {
          "_id": 2,
          "id": "credit",
          "name": "信用点",
          "amount": 50000
        },
        {
          "_id": 110142,
          "id": "oath_of_steel",
          "name": "寒铁的誓言",
          "amount": 8
        },
        {
          "_id": 111002,
          "id": "glimmering_core",
          "name": "微光原核",
          "amount": 12
        }
      ]
    },
    {
      "promotion": 4,
      "maxLevel": 60,
      "attackBase": 134.39999789119966,
      "attackAdd": 2.8799999556230023,
      "hpBase": 335.9999947270678,
      "hpAdd": 7.19999988719486,
      "defenseBase": 167.9999973635339,
      "defenseAdd": 3.599999944063091,
      "materials": [
        {
          "_id": 2,
          "id": "credit",
          "name": "信用点",
          "amount": 100000
        },
        {
          "_id": 110143,
          "id": "safeguard_of_amber",
          "name": "琥珀的坚守",
          "amount": 5
        },
        {
          "_id": 111003,
          "id": "squirming_core",
          "name": "蠢动原核",
          "amount": 6
        }
      ]
    },
    {
      "promotion": 5,
      "maxLevel": 70,
      "attackBase": 165.1199974088422,
      "attackAdd": 2.8799999556230023,
      "hpBase": 412.79999352257124,
      "hpAdd": 7.19999988719486,
      "defenseBase": 206.39999676128562,
      "defenseAdd": 3.599999944063091,
      "materials": [
        {
          "_id": 2,
          "id": "credit",
          "name": "信用点",
          "amount": 200000
        },
        {
          "_id": 110143,
          "id": "safeguard_of_amber",
          "name": "琥珀的坚守",
          "amount": 10
        },
        {
          "_id": 111003,
          "id": "squirming_core",
          "name": "蠢动原核",
          "amount": 8
        }
      ]
    },
    {
      "promotion": 6,
      "maxLevel": 80,
      "attackBase": 195.8399969274161,
      "attackAdd": 2.8799999556230023,
      "hpBase": 489.5999923171433,
      "hpAdd": 7.19999988719486,
      "defenseBase": 244.7999961590373,
      "defenseAdd": 3.599999944063091,
      "materials": []
    }
  ]
}
