{
  "_id": 23049,
  "id": "to_evernights_stars",
  "name": "A la estrella de la larga noche",
  "desc": "En los resquicios del tiempo solo resuena el latido de su corazón.\nIgual que tantas noches anteriores, observa la escena nocturna mientras descansa en ella.\n\nAtesora los recuerdos que le fueron confiados.\nDesde un punto de partida en blanco, la joven pinta con vívidos colores cada lugar donde se ha detenido. El acogedor tren, los compañeros de distintas personalidades, los planetas resplandecientes y hermosos... Es como un sueño hermoso del que no se quiere despertar.\n\n\"¡Mi verdadero viaje va a comenzar ahora!\".\nOye la declaración de la chica como si la tuviera al lado.\n\nMira hacia el lejano cielo estrellado, por donde se acerca un rayo de luz.\nEs el faro del tren, como si fuera una estrella fugaz.\n\n♭ \"Buenas noches, Marzo... El día que despiertes, continúa tu viaje trazando caminos\". ♭\n\nMientras sube la marea de recuerdos, ella guarda su deseo en lo más profundo de su corazón. Esos susurros y esa luz...\nNunca los ha olvidado.",
  "rarity": 5,
  "pathType": "Memory",
  "pathTypeText": "Reminiscencia",
  "effectName": "Insomnio",
  "effectTemplate": "Los PV máx. del portador aumentan en un <color=#f29e38ff>#1[i]%</color>. Cuando el mnemoduende del portador lanza una habilidad, el portador obtiene Escena nocturna. Cuando el portador tiene Escena nocturna, el daño que infligen todos los mnemoduendes aliados ignora el <color=#f29e38ff>#2[i]%</color> de la DEF de los objetivos y el daño que infligen el portador y su mnemoduende aumenta en un <color=#f29e38ff>#3[i]%</color>. Cuando el mnemoduende del portador desaparece, el portador recupera <color=#f29e38ff>#4[i]</color> pts. de energía. Los efectos del mismo tipo no se pueden acumular.",
  "superImpositions": [
    {
      "rank": 1,
      "params": [
        "30%",
        "20%",
        "30%",
        "8"
      ]
    },
    {
      "rank": 2,
      "params": [
        "38%",
        "23%",
        "38%",
        "10"
      ]
    },
    {
      "rank": 3,
      "params": [
        "45%",
        "25%",
        "45%",
        "12"
      ]
    },
    {
      "rank": 4,
      "params": [
        "53%",
        "28%",
        "53%",
        "14"
      ]
    },
    {
      "rank": 5,
      "params": [
        "60%",
        "30%",
        "60%",
        "16"
      ]
    }
  ],
  "ascend": [
    {
      "promotion": 0,
      "maxLevel": 20,
      "levelReq": 15,
      "attackBase": 24,
      "attackAdd": 3.6,
      "hpBase": 52.8,
      "hpAdd": 7.92,
      "defenseBase": 21,
      "defenseAdd": 3.15,
      "materials": [
        {
          "_id": 2,
          "id": "credit",
          "name": "Crédito",
          "amount": 5000
        },
        {
          "_id": 115011,
          "id": "ethereal_omen",
          "name": "Augurio etéreo",
          "amount": 8
        }
      ]
    },
    {
      "promotion": 1,
      "maxLevel": 30,
      "attackBase": 52.8,
      "attackAdd": 3.6,
      "hpBase": 116.16,
      "hpAdd": 7.92,
      "defenseBase": 46.2,
      "defenseAdd": 3.15,
      "materials": [
        {
          "_id": 2,
          "id": "credit",
          "name": "Crédito",
          "amount": 10000
        },
        {
          "_id": 110251,
          "id": "bja_of_consciousness",
          "name": "Semilla de la reflexión",
          "amount": 4
        },
        {
          "_id": 115011,
          "id": "ethereal_omen",
          "name": "Augurio etéreo",
          "amount": 12
        }
      ]
    },
    {
      "promotion": 2,
      "maxLevel": 40,
      "attackBase": 91.2,
      "attackAdd": 3.6,
      "hpBase": 200.64,
      "hpAdd": 7.92,
      "defenseBase": 79.8,
      "defenseAdd": 3.15,
      "materials": [
        {
          "_id": 2,
          "id": "credit",
          "name": "Crédito",
          "amount": 20000
        },
        {
          "_id": 110252,
          "id": "seedling_of_manas",
          "name": "Brote de manas",
          "amount": 4
        },
        {
          "_id": 115012,
          "id": "echoing_wail",
          "name": "Gemido resonante",
          "amount": 8
        }
      ]
    },
    {
      "promotion": 3,
      "maxLevel": 50,
      "attackBase": 129.6,
      "attackAdd": 3.6,
      "hpBase": 285.12,
      "hpAdd": 7.92,
      "defenseBase": 113.4,
      "defenseAdd": 3.15,
      "materials": [
        {
          "_id": 2,
          "id": "credit",
          "name": "Crédito",
          "amount": 50000
        },
        {
          "_id": 110252,
          "id": "seedling_of_manas",
          "name": "Brote de manas",
          "amount": 8
        },
        {
          "_id": 115012,
          "id": "echoing_wail",
          "name": "Gemido resonante",
          "amount": 12
        }
      ]
    },
    {
      "promotion": 4,
      "maxLevel": 60,
      "attackBase": 168,
      "attackAdd": 3.6,
      "hpBase": 369.6,
      "hpAdd": 7.92,
      "defenseBase": 147,
      "defenseAdd": 3.15,
      "materials": [
        {
          "_id": 2,
          "id": "credit",
          "name": "Crédito",
          "amount": 100000
        },
        {
          "_id": 110253,
          "id": "flower_of_laya",
          "name": "Alayawah",
          "amount": 5
        },
        {
          "_id": 115013,
          "id": "eternal_lament",
          "name": "Lamento eterno",
          "amount": 6
        }
      ]
    },
    {
      "promotion": 5,
      "maxLevel": 70,
      "attackBase": 206.4,
      "attackAdd": 3.6,
      "hpBase": 454.08,
      "hpAdd": 7.92,
      "defenseBase": 180.6,
      "defenseAdd": 3.15,
      "materials": [
        {
          "_id": 2,
          "id": "credit",
          "name": "Crédito",
          "amount": 200000
        },
        {
          "_id": 110253,
          "id": "flower_of_laya",
          "name": "Alayawah",
          "amount": 10
        },
        {
          "_id": 115013,
          "id": "eternal_lament",
          "name": "Lamento eterno",
          "amount": 8
        }
      ]
    },
    {
      "promotion": 6,
      "maxLevel": 80,
      "attackBase": 244.8,
      "attackAdd": 3.6,
      "hpBase": 538.56,
      "hpAdd": 7.92,
      "defenseBase": 214.2,
      "defenseAdd": 3.15,
      "materials": []
    }
  ]
}