{
  "_id": 213,
  "id": "travelers_guide",
  "name": "Guia do Viajante",
  "description": "Material de experiência para personagens. É possível obter 20.000 de EXP de Personagem.",
  "story": "Leitura obrigatória para explorar o mundo. Pressione o botão \"Ler\" para reproduzir uma voz atraente num idioma que você entenda falando sobre os encontros lendários de aventureiros renomados em diferentes mundos, bem como a sabedoria e o conhecimento precioso que eles acumularam.\n\n\"A novíssima série do Guia do Viajante, 'Manual de Gastronomia Galáctica do Chefe', já está disponível para compra.\"\n\"Para fazer pedidos, envie um sinal de sinestesia para ERD-23θ e entre em contato com um representante da Guilda de Intelectuais. Temos várias formas de pagamento.\"",
  "rarity": 5,
  "source": [
    {
      "description": "Cálice (Planícies Nevadas Distantes)",
      "recipe": []
    },
    {
      "description": "Cálice: Vau-nuvem",
      "recipe": []
    },
    {
      "description": "Cálice: Margem do Sonho",
      "recipe": []
    },
    {
      "description": "Salão Esquecido",
      "recipe": []
    }
  ],
  "type": {
    "id": 1,
    "name": "Material de EXP de Personagem"
  }
}